{
  "team_id": 12376,
  "team_name": "m80",
  "date_range": [
    "2025-03-15",
    "2025-05-14"
  ],
  "self_ranking": {
    "rank": 21,
    "points": 56
  },
  "recent_matches": [
    [
      {
        "format": "bo3"
      },
      {
        "date": "2025-05-12",
        "event": "PGL Astana 2025",
        "opponent": "G2",
        "team": "m80",
        "map": "Ancient",
        "result": "13 - 9",
        "match_url": "https://www.hltv.org/stats/matches/mapstatsid/199504/g2-vs-m80?startDate=2025-03-15&endDate=2025-05-14&contextIds=12376&contextTypes=team&rankingFilter=Top50",
        "opponent_ranking": {
          "rank": 8,
          "points": 309
        }
      },
      {
        "date": "2025-05-12",
        "event": "PGL Astana 2025",
        "opponent": "G2",
        "team": "m80",
        "map": "Dust2",
        "result": "11 - 13",
        "match_url": "https://www.hltv.org/stats/matches/mapstatsid/199501/m80-vs-g2?startDate=2025-03-15&endDate=2025-05-14&contextIds=12376&contextTypes=team&rankingFilter=Top50",
        "opponent_ranking": {
          "rank": 8,
          "points": 309
        }
      },
      {
        "date": "2025-05-12",
        "event": "PGL Astana 2025",
        "opponent": "G2",
        "team": "m80",
        "map": "Inferno",
        "result": "10 - 13",
        "match_url": "https://www.hltv.org/stats/matches/mapstatsid/199511/m80-vs-g2?startDate=2025-03-15&endDate=2025-05-14&contextIds=12376&contextTypes=team&rankingFilter=Top50",
        "opponent_ranking": {
          "rank": 8,
          "points": 309
        },
        "series_score": "1-2"
      }
    ],
    [
      {
        "format": "bo3"
      },
      {
        "date": "2025-05-11",
        "event": "PGL Astana 2025",
        "opponent": "Virtus.Pro",
        "team": "m80",
        "map": "Ancient",
        "result": "13 - 9",
        "match_url": "https://www.hltv.org/stats/matches/mapstatsid/199396/virtuspro-vs-m80?startDate=2025-03-15&endDate=2025-05-14&contextIds=12376&contextTypes=team&rankingFilter=Top50",
        "opponent_ranking": {
          "rank": 12,
          "points": 157
        }
      },
      {
        "date": "2025-05-11",
        "event": "PGL Astana 2025",
        "opponent": "Virtus.Pro",
        "team": "m80",
        "map": "Inferno",
        "result": "10 - 13",
        "match_url": "https://www.hltv.org/stats/matches/mapstatsid/199401/virtuspro-vs-m80?startDate=2025-03-15&endDate=2025-05-14&contextIds=12376&contextTypes=team&rankingFilter=Top50",
        "opponent_ranking": {
          "rank": 12,
          "points": 157
        }
      },
      {
        "date": "2025-05-11",
        "event": "PGL Astana 2025",
        "opponent": "Virtus.Pro",
        "team": "m80",
        "map": "Mirage",
        "result": "8 - 13",
        "match_url": "https://www.hltv.org/stats/matches/mapstatsid/199398/m80-vs-virtuspro?startDate=2025-03-15&endDate=2025-05-14&contextIds=12376&contextTypes=team&rankingFilter=Top50",
        "opponent_ranking": {
          "rank": 12,
          "points": 157
        },
        "series_score": "1-2"
      }
    ],
    [
      {
        "format": "bo3"
      },
      {
        "date": "2025-05-10",
        "event": "PGL Astana 2025",
        "opponent": "Natus Vincere",
        "team": "m80",
        "map": "Dust2",
        "result": "4 - 13",
        "match_url": "https://www.hltv.org/stats/matches/mapstatsid/199344/natus-vincere-vs-m80?startDate=2025-03-15&endDate=2025-05-14&contextIds=12376&contextTypes=team&rankingFilter=Top50",
        "opponent_ranking": {
          "rank": 6,
          "points": 347
        }
      },
      {
        "date": "2025-05-10",
        "event": "PGL Astana 2025",
        "opponent": "Natus Vincere",
        "team": "m80",
        "map": "Mirage",
        "result": "7 - 13",
        "match_url": "https://www.hltv.org/stats/matches/mapstatsid/199349/m80-vs-natus-vincere?startDate=2025-03-15&endDate=2025-05-14&contextIds=12376&contextTypes=team&rankingFilter=Top50",
        "opponent_ranking": {
          "rank": 6,
          "points": 347
        },
        "series_score": "0-2"
      }
    ],
    [
      {
        "format": "bo5"
      },
      {
        "date": "2025-04-01",
        "event": "PGL Astana 2025 North America Closed Qualifier",
        "opponent": "Bluejays",
        "team": "m80",
        "map": "Ancient",
        "result": "13 - 8",
        "match_url": "https://www.hltv.org/stats/matches/mapstatsid/196875/m80-vs-bluejays?startDate=2025-03-15&endDate=2025-05-14&contextIds=12376&contextTypes=team&rankingFilter=Top50",
        "opponent_ranking": {
          "rank": 52,
          "points": 15
        }
      },
      {
        "date": "2025-04-01",
        "event": "PGL Astana 2025 North America Closed Qualifier",
        "opponent": "Bluejays",
        "team": "m80",
        "map": "Dust2",
        "result": "16 - 13",
        "match_url": "https://www.hltv.org/stats/matches/mapstatsid/196872/bluejays-vs-m80?startDate=2025-03-15&endDate=2025-05-14&contextIds=12376&contextTypes=team&rankingFilter=Top50",
        "opponent_ranking": {
          "rank": 52,
          "points": 15
        }
      },
      {
        "date": "2025-04-01",
        "event": "PGL Astana 2025 North America Closed Qualifier",
        "opponent": "Bluejays",
        "team": "m80",
        "map": "Mirage",
        "result": "13 - 10",
        "match_url": "https://www.hltv.org/stats/matches/mapstatsid/196882/bluejays-vs-m80?startDate=2025-03-15&endDate=2025-05-14&contextIds=12376&contextTypes=team&rankingFilter=Top50",
        "opponent_ranking": {
          "rank": 52,
          "points": 15
        }
      },
      {
        "date": "2025-04-01",
        "event": "PGL Astana 2025 North America Closed Qualifier",
        "opponent": "Bluejays",
        "team": "m80",
        "map": "Train",
        "result": "10 - 13",
        "match_url": "https://www.hltv.org/stats/matches/mapstatsid/196866/m80-vs-bluejays?startDate=2025-03-15&endDate=2025-05-14&contextIds=12376&contextTypes=team&rankingFilter=Top50",
        "opponent_ranking": {
          "rank": 52,
          "points": 15
        },
        "series_score": "3-1"
      }
    ],
    [
      {
        "format": "bo3"
      },
      {
        "date": "2025-03-31",
        "event": "PGL Astana 2025 North America Closed Qualifier",
        "opponent": "Wildcard",
        "team": "m80",
        "map": "Inferno",
        "result": "13 - 4",
        "match_url": "https://www.hltv.org/stats/matches/mapstatsid/196798/m80-vs-wildcard?startDate=2025-03-15&endDate=2025-05-14&contextIds=12376&contextTypes=team&rankingFilter=Top50",
        "opponent_ranking": {
          "rank": 22,
          "points": 54
        }
      },
      {
        "date": "2025-03-31",
        "event": "PGL Astana 2025 North America Closed Qualifier",
        "opponent": "Wildcard",
        "team": "m80",
        "map": "Mirage",
        "result": "19 - 15",
        "match_url": "https://www.hltv.org/stats/matches/mapstatsid/196795/wildcard-vs-m80?startDate=2025-03-15&endDate=2025-05-14&contextIds=12376&contextTypes=team&rankingFilter=Top50",
        "opponent_ranking": {
          "rank": 22,
          "points": 54
        },
        "series_score": "2-0"
      }
    ],
    [
      {
        "format": "bo3"
      },
      {
        "date": "2025-03-31",
        "event": "PGL Astana 2025 North America Closed Qualifier",
        "opponent": "Marsborne",
        "team": "m80",
        "map": "Dust2",
        "result": "13 - 5",
        "match_url": "https://www.hltv.org/stats/matches/mapstatsid/196755/marsborne-vs-m80?startDate=2025-03-15&endDate=2025-05-14&contextIds=12376&contextTypes=team&rankingFilter=Top50",
        "opponent_ranking": {
          "rank": 60,
          "points": 12
        }
      },
      {
        "date": "2025-03-31",
        "event": "PGL Astana 2025 North America Closed Qualifier",
        "opponent": "Marsborne",
        "team": "m80",
        "map": "Train",
        "result": "13 - 11",
        "match_url": "https://www.hltv.org/stats/matches/mapstatsid/196757/m80-vs-marsborne?startDate=2025-03-15&endDate=2025-05-14&contextIds=12376&contextTypes=team&rankingFilter=Top50",
        "opponent_ranking": {
          "rank": 60,
          "points": 12
        },
        "series_score": "2-0"
      }
    ],
    [
      {
        "format": "bo3"
      },
      {
        "date": "2025-03-29",
        "event": "PGL Astana 2025 North America Closed Qualifier",
        "opponent": "Marsborne",
        "team": "m80",
        "map": "Ancient",
        "result": "13 - 3",
        "match_url": "https://www.hltv.org/stats/matches/mapstatsid/196629/marsborne-vs-m80?startDate=2025-03-15&endDate=2025-05-14&contextIds=12376&contextTypes=team&rankingFilter=Top50",
        "opponent_ranking": {
          "rank": 60,
          "points": 12
        }
      },
      {
        "date": "2025-03-29",
        "event": "PGL Astana 2025 North America Closed Qualifier",
        "opponent": "Marsborne",
        "team": "m80",
        "map": "Dust2",
        "result": "13 - 3",
        "match_url": "https://www.hltv.org/stats/matches/mapstatsid/196612/marsborne-vs-m80?startDate=2025-03-15&endDate=2025-05-14&contextIds=12376&contextTypes=team&rankingFilter=Top50",
        "opponent_ranking": {
          "rank": 60,
          "points": 12
        }
      },
      {
        "date": "2025-03-29",
        "event": "PGL Astana 2025 North America Closed Qualifier",
        "opponent": "Marsborne",
        "team": "m80",
        "map": "Train",
        "result": "5 - 13",
        "match_url": "https://www.hltv.org/stats/matches/mapstatsid/196628/m80-vs-marsborne?startDate=2025-03-15&endDate=2025-05-14&contextIds=12376&contextTypes=team&rankingFilter=Top50",
        "opponent_ranking": {
          "rank": 60,
          "points": 12
        },
        "series_score": "2-1"
      }
    ],
    [
      {
        "format": "bo3"
      },
      {
        "date": "2025-03-23",
        "event": "BLAST Open Lisbon 2025",
        "opponent": "G2",
        "team": "m80",
        "map": "Ancient",
        "result": "9 - 13",
        "match_url": "https://www.hltv.org/stats/matches/mapstatsid/195939/g2-vs-m80?startDate=2025-03-15&endDate=2025-05-14&contextIds=12376&contextTypes=team&rankingFilter=Top50",
        "opponent_ranking": {
          "rank": 8,
          "points": 309
        }
      },
      {
        "date": "2025-03-23",
        "event": "BLAST Open Lisbon 2025",
        "opponent": "G2",
        "team": "m80",
        "map": "Inferno",
        "result": "11 - 13",
        "match_url": "https://www.hltv.org/stats/matches/mapstatsid/195940/m80-vs-g2?startDate=2025-03-15&endDate=2025-05-14&contextIds=12376&contextTypes=team&rankingFilter=Top50",
        "opponent_ranking": {
          "rank": 8,
          "points": 309
        },
        "series_score": "0-2"
      }
    ],
    [
      {
        "format": "bo3"
      },
      {
        "date": "2025-03-22",
        "event": "BLAST Open Lisbon 2025",
        "opponent": "Furia",
        "team": "m80",
        "map": "Dust2",
        "result": "7 - 13",
        "match_url": "https://www.hltv.org/stats/matches/mapstatsid/195838/m80-vs-furia?startDate=2025-03-15&endDate=2025-05-14&contextIds=12376&contextTypes=team&rankingFilter=Top50",
        "opponent_ranking": {
          "rank": 19,
          "points": 62
        }
      },
      {
        "date": "2025-03-22",
        "event": "BLAST Open Lisbon 2025",
        "opponent": "Furia",
        "team": "m80",
        "map": "Inferno",
        "result": "19 - 17",
        "match_url": "https://www.hltv.org/stats/matches/mapstatsid/195860/m80-vs-furia?startDate=2025-03-15&endDate=2025-05-14&contextIds=12376&contextTypes=team&rankingFilter=Top50",
        "opponent_ranking": {
          "rank": 19,
          "points": 62
        }
      },
      {
        "date": "2025-03-22",
        "event": "BLAST Open Lisbon 2025",
        "opponent": "Furia",
        "team": "m80",
        "map": "Train",
        "result": "13 - 10",
        "match_url": "https://www.hltv.org/stats/matches/mapstatsid/195842/m80-vs-furia?startDate=2025-03-15&endDate=2025-05-14&contextIds=12376&contextTypes=team&rankingFilter=Top50",
        "opponent_ranking": {
          "rank": 19,
          "points": 62
        },
        "series_score": "2-1"
      }
    ],
    [
      {
        "format": "bo3"
      },
      {
        "date": "2025-03-20",
        "event": "BLAST Open Lisbon 2025",
        "opponent": "The Mongolz",
        "team": "m80",
        "map": "Ancient",
        "result": "13 - 11",
        "match_url": "https://www.hltv.org/stats/matches/mapstatsid/195741/m80-vs-the-mongolz?startDate=2025-03-15&endDate=2025-05-14&contextIds=12376&contextTypes=team&rankingFilter=Top50",
        "opponent_ranking": {
          "rank": 7,
          "points": 343
        }
      },
      {
        "date": "2025-03-20",
        "event": "BLAST Open Lisbon 2025",
        "opponent": "The Mongolz",
        "team": "m80",
        "map": "Dust2",
        "result": "11 - 13",
        "match_url": "https://www.hltv.org/stats/matches/mapstatsid/195739/the-mongolz-vs-m80?startDate=2025-03-15&endDate=2025-05-14&contextIds=12376&contextTypes=team&rankingFilter=Top50",
        "opponent_ranking": {
          "rank": 7,
          "points": 343
        }
      },
      {
        "date": "2025-03-20",
        "event": "BLAST Open Lisbon 2025",
        "opponent": "The Mongolz",
        "team": "m80",
        "map": "Inferno",
        "result": "3 - 13",
        "match_url": "https://www.hltv.org/stats/matches/mapstatsid/195745/the-mongolz-vs-m80?startDate=2025-03-15&endDate=2025-05-14&contextIds=12376&contextTypes=team&rankingFilter=Top50",
        "opponent_ranking": {
          "rank": 7,
          "points": 343
        },
        "series_score": "1-2"
      }
    ]
  ],
  "map_stats": {
    "Dust2": {
      "winrate": 0.429,
      "pick_pct": 0.75,
      "ban_pct": 0.091,
      "maps_played": 7
    },
    "Inferno": {
      "winrate": 0.33299999999999996,
      "pick_pct": 0.0,
      "ban_pct": 0.0,
      "maps_played": 6
    },
    "Ancient": {
      "winrate": 0.833,
      "pick_pct": 0.429,
      "ban_pct": 0.0,
      "maps_played": 6
    },
    "Mirage": {
      "winrate": 0.5,
      "pick_pct": 0.222,
      "ban_pct": 0.28600000000000003,
      "maps_played": 4
    },
    "Train": {
      "winrate": 0.5,
      "pick_pct": 0.0,
      "ban_pct": 0.091,
      "maps_played": 4
    }
  },
  "player_stats": [
    {
      "name": "Lake",
      "maps": 27,
      "kd": 0.97,
      "rating": 1.06
    },
    {
      "name": "slaxz-",
      "maps": 27,
      "kd": 1.13,
      "rating": 1.06
    },
    {
      "name": "s1n",
      "maps": 27,
      "kd": 0.99,
      "rating": 1.03
    },
    {
      "name": "Swisher",
      "maps": 27,
      "kd": 0.89,
      "rating": 0.97
    },
    {
      "name": "reck",
      "maps": 27,
      "kd": 0.93,
      "rating": 0.94
    }
  ]
}